ezbuff/__init__.py
ezbuff-1.0.dist-info/LICENSE.txt
ezbuff-1.0.dist-info/METADATA
ezbuff-1.0.dist-info/WHEEL
ezbuff-1.0.dist-info/top_level.txt
ezbuff-1.0.dist-info/RECORD
