Metadata-Version: 2.1
Name: ezbuff
Version: 1.0
Summary: Ezbuff is a Python package created to automate some steps of the 2020 PWK buffer overflow.
Home-page: https://github.com/binexisHATT/Ezfuzz
Author: Alexis Rodriguez
Author-email: rodriguez10011999@gmail.com
License: MIT
Platform: UNKNOWN
Classifier: Programming Language :: Python :: 3
Classifier: License :: OSI Approved :: MIT License
Classifier: Operating System :: OS Independent
Requires-Python: >=3.6
